CHANGES.txt
LICENSE.txt
MANIFEST.in
README.txt
setup.cfg
setup.py
sqlahelper.py
SQLAHelper.egg-info/PKG-INFO
SQLAHelper.egg-info/SOURCES.txt
SQLAHelper.egg-info/dependency_links.txt
SQLAHelper.egg-info/entry_points.txt
SQLAHelper.egg-info/not-zip-safe
SQLAHelper.egg-info/requires.txt
SQLAHelper.egg-info/top_level.txt
docs/Makefile
docs/changes.rst
docs/conf.py
docs/index.rst
docs/release.txt
docs/usage.rst
docs/_themes/.gitignore
docs/_themes/CONTRIBUTORS.txt
docs/_themes/LICENSE.txt
docs/_themes/README.rst
docs/_themes/pylons_theme_support.py
docs/_themes/.git/HEAD
docs/_themes/.git/config
docs/_themes/.git/description
docs/_themes/.git/index
docs/_themes/.git/packed-refs
docs/_themes/.git/hooks/applypatch-msg.sample
docs/_themes/.git/hooks/commit-msg.sample
docs/_themes/.git/hooks/post-commit.sample
docs/_themes/.git/hooks/post-receive.sample
docs/_themes/.git/hooks/post-update.sample
docs/_themes/.git/hooks/pre-applypatch.sample
docs/_themes/.git/hooks/pre-commit.sample
docs/_themes/.git/hooks/pre-rebase.sample
docs/_themes/.git/hooks/prepare-commit-msg.sample
docs/_themes/.git/hooks/update.sample
docs/_themes/.git/info/exclude
docs/_themes/.git/logs/HEAD
docs/_themes/.git/logs/refs/heads/master
docs/_themes/.git/objects/pack/pack-9396d5373248fdaca0f96b23f27da9244e11aefc.idx
docs/_themes/.git/objects/pack/pack-9396d5373248fdaca0f96b23f27da9244e11aefc.pack
docs/_themes/.git/refs/heads/master
docs/_themes/.git/refs/remotes/origin/HEAD
docs/_themes/pylons/layout.html
docs/_themes/pylons/theme.conf
docs/_themes/pylons/static/dialog-note.png
docs/_themes/pylons/static/dialog-seealso.png
docs/_themes/pylons/static/dialog-topic.png
docs/_themes/pylons/static/dialog-warning.png
docs/_themes/pylons/static/epub.css
docs/_themes/pylons/static/footerbg.png
docs/_themes/pylons/static/headerbg.png
docs/_themes/pylons/static/ie6.css
docs/_themes/pylons/static/in_progress.png
docs/_themes/pylons/static/middlebg.png
docs/_themes/pylons/static/pylons-latex.png
docs/_themes/pylons/static/pylons-small.png
docs/_themes/pylons/static/pylons.css_t
docs/_themes/pylons/static/pylons.ico
docs/_themes/pylons/static/pylons.png
docs/_themes/pylons/static/transparent.gif
docs/_themes/pylonsfw/theme.conf
