Metadata-Version: 1.0
Name: SQLAHelper
Version: 1.0
Summary: A convenience library for SQLAlchemy web applications
Home-page: http://bitbucket.org/sluggo/sqlahelper
Author: Mike Orr
Author-email: sluggoster@gmail.com
License: MIT
Platform: UNKNOWN
Classifier: Intended Audience :: Developers
Classifier: Programming Language :: Python
Classifier: License :: OSI Approved :: MIT License
Classifier: Topic :: Database
